[
  {
    "group_name": "Marketing_Group_01",
    "group_category": "Distribution",
    "group_scope": "DomainLocal",
    "group_description": "Team collaboration group for Teams and SharePoint.",
    "distinguished_name": "CN=Marketing_Group_01,OU=Marketing,DC=corp,DC=local",
    "organizational_unit": "OU=Marketing,DC=corp,DC=local",
    "etlid": 1,
    "Extension_Attribute_1": "MAR-1001",
    "Group_Created": "2021-07-02 23:16:45",
    "Group_Modified": "2023-05-10 06:39:38",
    "Extension_Attribute_9": "EXT-15082"
  },
  {
    "group_name": "Sales_Group_02",
    "group_category": "Distribution",
    "group_scope": "DomainLocal",
    "group_description": "Security group for file server access.",
    "distinguished_name": "CN=Sales_Group_02,OU=Sales,DC=corp,DC=local",
    "organizational_unit": "OU=Sales,DC=corp,DC=local",
    "etlid": 2,
    "Extension_Attribute_1": "SAL-1002",
    "Group_Created": "2023-07-28 21:24:39",
    "Group_Modified": "2024-11-18 00:42:33",
    "Extension_Attribute_9": "EXT-78164"
  },
  {
    "group_name": "HR_Group_03",
    "group_category": "Security",
    "group_scope": "Universal",
    "group_description": "Team collaboration group for Teams and SharePoint.",
    "distinguished_name": "CN=HR_Group_03,OU=HR,DC=corp,DC=local",
    "organizational_unit": "OU=HR,DC=corp,DC=local",
    "etlid": 3,
    "Extension_Attribute_1": "HR-1003",
    "Group_Created": "2023-04-03 00:27:12",
    "Group_Modified": "2022-08-18 11:47:22",
    "Extension_Attribute_9": "EXT-78466"
  },
  {
    "group_name": "IT_Group_04",
    "group_category": "Security",
    "group_scope": "Universal",
    "group_description": "Access control for department resources.",
    "distinguished_name": "CN=IT_Group_04,OU=IT,DC=corp,DC=local",
    "organizational_unit": "OU=IT,DC=corp,DC=local",
    "etlid": 4,
    "Extension_Attribute_1": "IT-1004",
    "Group_Created": "2024-01-11 23:38:16",
    "Group_Modified": "2024-06-02 03:26:15",
    "Extension_Attribute_9": "EXT-18956"
  },
  {
    "group_name": "Support_Group_05",
    "group_category": "Security",
    "group_scope": "Global",
    "group_description": "Email distribution group for announcements.",
    "distinguished_name": "CN=Support_Group_05,OU=Support,DC=corp,DC=local",
    "organizational_unit": "OU=Support,DC=corp,DC=local",
    "etlid": 5,
    "Extension_Attribute_1": "SUP-1005",
    "Group_Created": "2021-12-09 19:28:49",
    "Group_Modified": "2025-02-01 14:03:07",
    "Extension_Attribute_9": "EXT-90483"
  },
  {
    "group_name": "Sales_Group_06",
    "group_category": "Security",
    "group_scope": "Global",
    "group_description": "Access control for department resources.",
    "distinguished_name": "CN=Sales_Group_06,OU=Sales,DC=corp,DC=local",
    "organizational_unit": "OU=Sales,DC=corp,DC=local",
    "etlid": 6,
    "Extension_Attribute_1": "SAL-1006",
    "Group_Created": "2025-05-24 13:25:43",
    "Group_Modified": "2021-05-08 09:22:17",
    "Extension_Attribute_9": "EXT-93171"
  },
  {
    "group_name": "Engineering_Group_07",
    "group_category": "Distribution",
    "group_scope": "Global",
    "group_description": "Team collaboration group for Teams and SharePoint.",
    "distinguished_name": "CN=Engineering_Group_07,OU=Engineering,DC=corp,DC=local",
    "organizational_unit": "OU=Engineering,DC=corp,DC=local",
    "etlid": 7,
    "Extension_Attribute_1": "ENG-1007",
    "Group_Created": "2021-11-01 21:46:57",
    "Group_Modified": "2021-10-12 11:12:13",
    "Extension_Attribute_9": "EXT-66302"
  },
  {
    "group_name": "Operations_Group_08",
    "group_category": "Distribution",
    "group_scope": "Universal",
    "group_description": "Team collaboration group for Teams and SharePoint.",
    "distinguished_name": "CN=Operations_Group_08,OU=Operations,DC=corp,DC=local",
    "organizational_unit": "OU=Operations,DC=corp,DC=local",
    "etlid": 8,
    "Extension_Attribute_1": "OPE-1008",
    "Group_Created": "2025-08-18 08:13:28",
    "Group_Modified": "2021-10-25 14:27:05",
    "Extension_Attribute_9": "EXT-78591"
  },
  {
    "group_name": "Support_Group_09",
    "group_category": "Security",
    "group_scope": "DomainLocal",
    "group_description": "Security group for file server access.",
    "distinguished_name": "CN=Support_Group_09,OU=Support,DC=corp,DC=local",
    "organizational_unit": "OU=Support,DC=corp,DC=local",
    "etlid": 9,
    "Extension_Attribute_1": "SUP-1009",
    "Group_Created": "2022-02-10 12:08:37",
    "Group_Modified": "2021-06-08 12:47:44",
    "Extension_Attribute_9": "EXT-63243"
  },
  {
    "group_name": "Marketing_Group_10",
    "group_category": "Security",
    "group_scope": "Global",
    "group_description": "Email distribution group for announcements.",
    "distinguished_name": "CN=Marketing_Group_10,OU=Marketing,DC=corp,DC=local",
    "organizational_unit": "OU=Marketing,DC=corp,DC=local",
    "etlid": 10,
    "Extension_Attribute_1": "MAR-1010",
    "Group_Created": "2025-09-10 05:29:30",
    "Group_Modified": "2022-10-17 07:12:00",
    "Extension_Attribute_9": "EXT-91321"
  },
  {
    "group_name": "IT_Group_11",
    "group_category": "Security",
    "group_scope": "Universal",
    "group_description": "Group for VPN and network privileges.",
    "distinguished_name": "CN=IT_Group_11,OU=IT,DC=corp,DC=local",
    "organizational_unit": "OU=IT,DC=corp,DC=local",
    "etlid": 11,
    "Extension_Attribute_1": "IT-1011",
    "Group_Created": "2025-08-07 09:24:59",
    "Group_Modified": "2022-05-02 08:01:49",
    "Extension_Attribute_9": "EXT-15078"
  },
  {
    "group_name": "Engineering_Group_12",
    "group_category": "Distribution",
    "group_scope": "Global",
    "group_description": "Group for VPN and network privileges.",
    "distinguished_name": "CN=Engineering_Group_12,OU=Engineering,DC=corp,DC=local",
    "organizational_unit": "OU=Engineering,DC=corp,DC=local",
    "etlid": 12,
    "Extension_Attribute_1": "ENG-1012",
    "Group_Created": "2021-03-13 08:32:13",
    "Group_Modified": "2024-02-02 10:38:23",
    "Extension_Attribute_9": "EXT-81372"
  },
  {
    "group_name": "Support_Group_13",
    "group_category": "Security",
    "group_scope": "Global",
    "group_description": "Access control for department resources.",
    "distinguished_name": "CN=Support_Group_13,OU=Support,DC=corp,DC=local",
    "organizational_unit": "OU=Support,DC=corp,DC=local",
    "etlid": 13,
    "Extension_Attribute_1": "SUP-1013",
    "Group_Created": "2025-03-04 19:08:46",
    "Group_Modified": "2021-05-16 13:05:34",
    "Extension_Attribute_9": "EXT-32603"
  },
  {
    "group_name": "HR_Group_14",
    "group_category": "Security",
    "group_scope": "Universal",
    "group_description": "Team collaboration group for Teams and SharePoint.",
    "distinguished_name": "CN=HR_Group_14,OU=HR,DC=corp,DC=local",
    "organizational_unit": "OU=HR,DC=corp,DC=local",
    "etlid": 14,
    "Extension_Attribute_1": "HR-1014",
    "Group_Created": "2025-09-16 19:36:45",
    "Group_Modified": "2024-03-11 03:52:34",
    "Extension_Attribute_9": "EXT-15889"
  },
  {
    "group_name": "Engineering_Group_15",
    "group_category": "Security",
    "group_scope": "DomainLocal",
    "group_description": "Security group for file server access.",
    "distinguished_name": "CN=Engineering_Group_15,OU=Engineering,DC=corp,DC=local",
    "organizational_unit": "OU=Engineering,DC=corp,DC=local",
    "etlid": 15,
    "Extension_Attribute_1": "ENG-1015",
    "Group_Created": "2023-04-01 14:45:48",
    "Group_Modified": "2023-03-29 02:21:03",
    "Extension_Attribute_9": "EXT-67300"
  },
  {
    "group_name": "Sales_Group_16",
    "group_category": "Security",
    "group_scope": "Universal",
    "group_description": "Group for VPN and network privileges.",
    "distinguished_name": "CN=Sales_Group_16,OU=Sales,DC=corp,DC=local",
    "organizational_unit": "OU=Sales,DC=corp,DC=local",
    "etlid": 16,
    "Extension_Attribute_1": "SAL-1016",
    "Group_Created": "2025-03-22 12:00:59",
    "Group_Modified": "2025-12-25 05:40:13",
    "Extension_Attribute_9": "EXT-88920"
  },
  {
    "group_name": "Finance_Group_17",
    "group_category": "Distribution",
    "group_scope": "Universal",
    "group_description": "Email distribution group for announcements.",
    "distinguished_name": "CN=Finance_Group_17,OU=Finance,DC=corp,DC=local",
    "organizational_unit": "OU=Finance,DC=corp,DC=local",
    "etlid": 17,
    "Extension_Attribute_1": "FIN-1017",
    "Group_Created": "2021-09-10 15:43:08",
    "Group_Modified": "2022-06-21 08:45:51",
    "Extension_Attribute_9": "EXT-83646"
  },
  {
    "group_name": "IT_Group_18",
    "group_category": "Distribution",
    "group_scope": "Universal",
    "group_description": "Security group for file server access.",
    "distinguished_name": "CN=IT_Group_18,OU=IT,DC=corp,DC=local",
    "organizational_unit": "OU=IT,DC=corp,DC=local",
    "etlid": 18,
    "Extension_Attribute_1": "IT-1018",
    "Group_Created": "2023-05-31 22:55:39",
    "Group_Modified": "2023-01-12 19:33:17",
    "Extension_Attribute_9": "EXT-41096"
  },
  {
    "group_name": "Finance_Group_19",
    "group_category": "Distribution",
    "group_scope": "Universal",
    "group_description": "Group for VPN and network privileges.",
    "distinguished_name": "CN=Finance_Group_19,OU=Finance,DC=corp,DC=local",
    "organizational_unit": "OU=Finance,DC=corp,DC=local",
    "etlid": 19,
    "Extension_Attribute_1": "FIN-1019",
    "Group_Created": "2025-01-16 03:37:59",
    "Group_Modified": "2025-12-06 23:04:43",
    "Extension_Attribute_9": "EXT-64547"
  },
  {
    "group_name": "HR_Group_20",
    "group_category": "Distribution",
    "group_scope": "DomainLocal",
    "group_description": "Security group for file server access.",
    "distinguished_name": "CN=HR_Group_20,OU=HR,DC=corp,DC=local",
    "organizational_unit": "OU=HR,DC=corp,DC=local",
    "etlid": 20,
    "Extension_Attribute_1": "HR-1020",
    "Group_Created": "2022-06-04 23:00:14",
    "Group_Modified": "2022-12-28 22:55:40",
    "Extension_Attribute_9": "EXT-19796"
  }
]